<annotation verified="yes">
    <folder>Annotation</folder>
    <filename>Screenshot_81.jpg</filename>
    <path>Fuel-Price-Types-New-PascalVOC-export/Annotations/Screenshot_81.jpg</path>
    <source>
        <database>Unknown</database>
    </source>
    <size>
        <width>1000</width>
        <height>700</height>
        <depth>3</depth>
    </size>
    <segmented>0</segmented>
    <object>
    <name>PB95</name>
    <pose>Unspecified</pose>
    <truncated>0</truncated>
    <difficult>0</difficult>
    <bndbox>
        <xmin>373.85836968375133</xmin>
        <ymin>54.51713395638629</ymin>
        <xmax>434.38181570338054</xmax>
        <ymax>133.5669781931464</ymax>
    </bndbox>
</object><object>
    <name>ON</name>
    <pose>Unspecified</pose>
    <truncated>0</truncated>
    <difficult>0</difficult>
    <bndbox>
        <xmin>371.1320883315158</xmin>
        <ymin>154.82866043613706</ymin>
        <xmax>434.38181570338054</xmax>
        <ymax>236.6043613707165</ymax>
    </bndbox>
</object><object>
    <name>LPG</name>
    <pose>Unspecified</pose>
    <truncated>0</truncated>
    <difficult>0</difficult>
    <bndbox>
        <xmin>367.31529443838605</xmin>
        <ymin>262.22741433021804</ymin>
        <xmax>432.20079062159215</xmax>
        <ymax>341.27725856697816</ymax>
    </bndbox>
</object><object>
    <name>PB98</name>
    <pose>Unspecified</pose>
    <truncated>0</truncated>
    <difficult>0</difficult>
    <bndbox>
        <xmin>370.58683206106866</xmin>
        <ymin>507.5545171339563</ymin>
        <xmax>431.11027808069787</xmax>
        <ymax>582.2429906542055</ymax>
    </bndbox>
</object><object>
    <name>ON</name>
    <pose>Unspecified</pose>
    <truncated>0</truncated>
    <difficult>0</difficult>
    <bndbox>
        <xmin>371.6773446019629</xmin>
        <ymin>611.1370716510903</ymin>
        <xmax>430.01976553980364</xmax>
        <ymax>691.2772585669782</ymax>
    </bndbox>
</object>
</annotation>
